Workbook

Sheet REFERENTIEL
A1: 🏛 RÉFÉRENTIEL — Districts & Assemblées | TLWM TOGO | Version 2026+
A2: ℹ️ Ce référentiel liste les districts et assemblées rattachées. À remplir ou mettre à jour par le superviseur de district.
A3: Code District | B3: Nom District | C3: Code Assemblée | D3: Nom Assemblée / Cellule | E3: Type Unité | F3: Pasteur / Responsable
A35: 💡 Codes District suggérés : D-LOM (Lomé), D-KPA (Kpalimé), D-ATA (Atakpamé), D-SOK (Sokodé), D-KAR (Kara), D-DAP (Dapaong), D-NOT (Notsé), D-TSE (Tsévié), D-ANE (Aného), D-VOG (Vogan), D-BAS (Bassar)

Sheet 1_IDENTIFICATION
A1: 🏢 RAPPORT MENSUEL — DISTRICT TLWM TOGO
A2: 📌 Version 2026+ | Un seul fichier par district par mois. Format standardisé TLWM.
A3: 📋 IDENTIFICATION DU RAPPORT
A4: Année | C4: Ex: 2026
A5: Mois | C5: Ex: Janvier
A6: Version du format | C6: V1-2026
A7: Code District | C7: Ex: D-LOM
A8: Nom District | C8: Ex: District Littoral (Lomé)
A9: Superviseur de District | C9: Nom et Prénom complet
A10: Contact Superviseur (téléphone) | C10: Ex: +228 9X XX XX XX
A11: Nombre d'assemblées actives | C11: Nombre entier
A12: Nombre de cellules actives | C12: Nombre entier
A13: Rapports assemblées reçus (nb/total) | C13: Ex: 4/5
A14: Date soumission au National | C14: JJ/MM/AAAA
A15: Statut du rapport | C15: Sélectionner dans la liste

Sheet 2_SYNTHESE_ASSEMBLEES
A1: 📊 SYNTHÈSE DES ASSEMBLÉES & CELLULES DU DISTRICT — Mois : ___________ Année : ______
A2: ℹ️ Une ligne par unité (Assemblée ou Cellule). Issues des rapports mensuels reçus. Les totaux sont calculés automatiquement.
A3: Code | B3: Nom Assemblée / Cellule | C3: Type | D3: Rapport Reçu | E3: Membres Actifs | F3: Ajoutés ce mois | G3: Sémin. en Asb | H3: Sémin. Hors Asb | I3: Assist. Cultes | J3: Assist. Mission | K3: Sauvés | L3: Témoig. | M3: Invités | N3: Prédicat. | O3: Pasteurs | P3: Recettes (FCFA) | Q3: Observations
A4: TOTAUX DISTRICT | E4: =IFERROR(SUM(E5:E32),0) | F4: =IFERROR(SUM(F5:F32),0) | G4: =IFERROR(SUM(G5:G32),0) | H4: =IFERROR(SUM(H5:H32),0) | I4: =IFERROR(SUM(I5:I32),0) | J4: =IFERROR(SUM(J5:J32),0) | K4: =IFERROR(SUM(K5:K32),0) | L4: =IFERROR(SUM(L5:L32),0) | ... P4: =IFERROR(SUM(P5:P32),0)

Sheet 3_ACTIVITES_DISTRICT
A1: ⚡ ACTIVITÉS PROPRES DU DISTRICT — Événements non imputables à une assemblée précise
A2: ℹ️ Saisir ici : Formations, CPPD, Réunions de pasteurs, Évangélisations de district, Séminaires inter-assemblées, etc. NE PAS inclure les activités propres à une assemblée particulière.
A3: Date | B3: Type d'activité | C3: Nom de l'activité | D3: Lieu | E3: Nb Jours | F3: Intervenant Principal | G3: Thème / Module | H3: Hommes | I3: Femmes | J3: Jeunes (- 25 ans) | K3: Assist. Totale | L3: Budget (FCFA) | M3: Dépenses (FCFA)
A4: TOTAUX | H4: =IFERROR(SUM(H5:H24),0) | I4: =IFERROR(SUM(I5:I24),0) | J4: =IFERROR(SUM(J5:J24),0) | K4: =IFERROR(SUM(K5:K24),0) | L4: =IFERROR(SUM(L5:L24),0) | M4: =IFERROR(SUM(M5:M24),0)
K5: =IFERROR(H5+I5+J5,"")
K6: =IFERROR(H6+I6+J6,"")
K7: =IFERROR(H7+I7+J7,"")
K8: =IFERROR(H8+I8+J8,"")
K9: =IFERROR(H9+I9+J9,"")
K10: =IFERROR(H10+I10+J10,"")
K11: =IFERROR(H11+I11+J11,"")
K12: =IFERROR(H12+I12+J12,"")
K13: =IFERROR(H13+I13+J13,"")
K14: =IFERROR(H14+I14+J14,"")
K15: =IFERROR(H15+I15+J15,"")
K16: =IFERROR(H16+I16+J16,"")
... K24: =IFERROR(H24+I24+J24,"")

Sheet 4_RESSOURCES_HUMAINES
A1: 👥 RESSOURCES HUMAINES — District (Snapshot fin de mois)
A2: ℹ️ Effectifs cumulés de toutes les assemblées + cellules du district. Les totaux des membres/pasteurs/prédicateurs sont tirés de l'onglet SYNTHESE.
A3: ① EFFECTIFS CUMULÉS DU DISTRICT (toutes assemblées + cellules)
A4: Total membres actifs (fin du mois) | B4: =IFERROR('2_SYNTHESE_ASSEMBLEES'!E4,"") | C4: =Onglet SYNTHESE, ligne TOTAUX, col. Membres Actifs
A5: Total ajoutés ce mois | B5: =IFERROR('2_SYNTHESE_ASSEMBLEES'!F4,"") | C5: =Onglet SYNTHESE, ligne TOTAUX, col. Ajoutés
A6: Total personnes sauvées ce mois | B6: =IFERROR('2_SYNTHESE_ASSEMBLEES'!K4,"") | C6: =Onglet SYNTHESE, ligne TOTAUX, col. Sauvés
A7: Total pasteurs (district + assemblées) | C7: Nombre total de pasteurs actifs
A8: Total prédicateurs accrédités | C8: Toutes assemblées confondues
A9: Prédicateurs en formation (école) | C9: Inscrits à l'école des prédicateurs
A10: Diacres / responsables GA (total) | C10: Responsables de groupes d'action
A11: Missionnaires affectés au district | C11: Nationaux ou internationaux
A12: ② STRUCTURE DU DISTRICT
A13: Nombre d'assemblées actives | C13: Ayant remis un rapport ce mois
A14: Nombre de cellules actives
A15: Nombre de groupes d'action (GA) total
A16: ③ MOUVEMENTS CE MOIS
A17: Nouveaux prédicateurs accrédités ce mois
A18: Prédicateurs diplômés de l'école ce mois
A19: Prédicateurs utilisés en mission ce mois
A20: Membres transférés entrants (toutes asb)
A21: Membres transférés sortants (toutes asb)
A22: Membres décédés ce mois (toutes asb)

Sheet 5_FINANCES
A1: 💰 FINANCES — District (FCFA) | Mois : ___________ Année : ______
A2: ℹ️ Toutes les valeurs sont en FCFA. Les recettes incluent les remontées des assemblées + dotations du National + autres recettes propres.
A3: ① RECETTES
A4: Total remontées des assemblées | B4: =IFERROR('2_SYNTHESE_ASSEMBLEES'!P4,"") | C4: =Onglet SYNTHESE, ligne TOTAUX, col. Recettes
A5: Dotation reçue du National (FCFA) | C5: Virement reçu du niveau national
A6: Autres recettes district (FCFA) | C6: Dons, partenariats, etc.
A7: TOTAL RECETTES | B7: =IFERROR(B4+B5+B6,0)
A8: ② DÉPENSES
A9: Dépenses activités propres district | B9: =IFERROR(SUM('3_ACTIVITES_DISTRICT'!M5:M24),"") | C9: Formations, CPPD, missions de district, QG
A10: Dépenses fonctionnement bureau district | C10: Loyer, frais bureau, communication
A11: Dotations redistribuées aux assemblées | C11: Aides versées aux assemblées
A12: TOTAL DÉPENSES | B12: =IFERROR(B9+B10+B11,0)
A13: ③ BILAN
A14: Remontée reversée au National | C14: Montant transféré au niveau national
A15: SOLDE DISTRICT (fin de mois) | B15: =IFERROR(B7-B12-B14,0) | C15: =Total Recettes - Total Dépenses - Remontée National
A16: ④ OBSERVATIONS FINANCES
A17: (Saisir ici les observations financières du mois : difficultés, retards, décisions prises...)

Sheet 6_REUSSITES_DIFFICULTES
A1: 🏆 RÉUSSITES, DIFFICULTÉS & PERSPECTIVES — District
A2: ℹ️ Inclure les points remontés par les assemblées + les observations propres au district. Structurer par type et catégorie.
A3: Type | B3: Catégorie | C3: Description détaillée | D3: Statut | E3: Actions / Suivi
A4: Réussite | B4: Mission & Évangélisation | C4: [EXEMPLE] École des prédicateurs : 15 diplômés ce mois | D4: Résolu | E4: Cérémonie de remise des diplômes organisée
A5: Difficulté | B5: Ressources Humaines | C5: [EXEMPLE] Manque de prédicateurs pour couvrir toutes les assemblées | D5: En cours | E5: Recrutement en cours — 3 candidats identifiés
A6: Perspective | B6: Formation & Éducation | C6: [EXEMPLE] Lancement session 2 de l'école des prédicateurs en Août | D6: Nouveau | E6: Budget à prévoir, salle à confirmer
